qh/__init__.py
qh/app.py
qh/async_endpoints.py
qh/async_tasks.py
qh/base.py
qh/client.py
qh/config.py
qh/conventions.py
qh/core.py
qh/endpoint.py
qh/jsclient.py
qh/openapi.py
qh/rules.py
qh/stores_qh.py
qh/testing.py
qh/types.py
qh/examples/__init__.py
qh/examples/async_example.py
qh/examples/simple.py
qh/scrap/__init__.py
qh/scrap/simple_fastapi_dispatch.py
qh/scrap/store_dispatch_1.py
qh/scrap/store_dispatch_2.py
qh/scrap/test_store_dispatch.py
qh/tests/test_async_tasks.py
qh/tests/test_base.py
qh/tests/test_conventions.py
qh/tests/test_core.py
qh/tests/test_jsclient.py
qh/tests/test_mk_app.py
qh/tests/test_openapi_client.py
qh/tests/test_round_trip.py
qh/tests/test_service_running.py
qh/tests/test_store_access.py
qh/tests/test_stores_qh.py
qh-0.0.9.dist-info/METADATA
qh-0.0.9.dist-info/WHEEL
qh-0.0.9.dist-info/licenses/LICENSE
qh-0.0.9.dist-info/RECORD
