Metadata-Version: 2.4
Name: qh
Version: 0.0.9
Summary: Quick Http web-service construction
Project-URL: Homepage, https://github.com/i2mint/qh
License: Apache-2.0
License-File: LICENSE
Keywords: framework,http,web-service
Requires-Python: >=3.10
Requires-Dist: fastapi>=0.100.0
Requires-Dist: i2
Requires-Dist: pydantic>=2.0.0
Requires-Dist: requests>=2.31.0
Requires-Dist: uvicorn>=0.23.0
Provides-Extra: dev
Requires-Dist: pytest-cov>=4.0; extra == 'dev'
Requires-Dist: pytest>=7.0; extra == 'dev'
Requires-Dist: ruff>=0.1.0; extra == 'dev'
Provides-Extra: docs
Requires-Dist: sphinx-rtd-theme>=1.0; extra == 'docs'
Requires-Dist: sphinx>=6.0; extra == 'docs'
